setup.py
PyPermissions.egg-info/PKG-INFO
PyPermissions.egg-info/SOURCES.txt
PyPermissions.egg-info/dependency_links.txt
PyPermissions.egg-info/top_level.txt
pypermissions/__init__.py
pypermissions/decorators.py
pypermissions/factory.py
pypermissions/permission.py
pypermissions/templates.py
tests/dynamic_permissions.py
tests/permission_decorators.py
tests/permission_factory.py
tests/permission_sets.py
tests/permission_template.py
tests/permissions.py