Metadata-Version: 1.1
Name: PyPermissions
Version: 0.1.1
Summary: An extensible permissions framework for granular access control.
Home-page: https://pypi.python.org/pypi/PyPermissions
Author: Tyler O'Meara
Author-email: Tyler@TylerOMeara.com
License: MIT
Keywords: permissions access control
Platform: UNKNOWN
Classifier: Development Status :: 3 - Alpha
Classifier: License :: OSI Approved :: MIT License
Classifier: Topic :: Software Development :: Libraries :: Python Modules
